openinference/instrumentation/smolagents/__init__.py
openinference/instrumentation/smolagents/_wrappers.py
openinference/instrumentation/smolagents/py.typed
openinference/instrumentation/smolagents/version.py
openinference_instrumentation_smolagents-0.1.20.dist-info/METADATA
openinference_instrumentation_smolagents-0.1.20.dist-info/WHEEL
openinference_instrumentation_smolagents-0.1.20.dist-info/entry_points.txt
openinference_instrumentation_smolagents-0.1.20.dist-info/licenses/LICENSE
openinference_instrumentation_smolagents-0.1.20.dist-info/RECORD
